setup.py
Jian.egg-info/PKG-INFO
Jian.egg-info/SOURCES.txt
Jian.egg-info/dependency_links.txt
Jian.egg-info/requires.txt
Jian.egg-info/top_level.txt
jian/__init__.py
jian/config.py
jian/core.py
jian/db.py
jian/enums.py
jian/exception.py
jian/forms.py
jian/interface.py
jian/jwt.py
jian/loader.py
jian/log.py
jian/notify.py
jian/plugin.py
jian/redprint.py
jian/sse.py
jian/util.py